pixelpotion/__init__.py
pixelpotion/cli.py
pixelpotion/convert.py
pixelpotion/split_frames.py
pixelpotion/utils.py
tests/__init__.py
tests/test_convert.py
tests/test_gif_split.py
pixelpotion-0.1.2.dist-info/METADATA
pixelpotion-0.1.2.dist-info/WHEEL
pixelpotion-0.1.2.dist-info/entry_points.txt
pixelpotion-0.1.2.dist-info/top_level.txt
pixelpotion-0.1.2.dist-info/RECORD
